odoo9_addon_mrp_bom_note-9.0.1.0.0.99.dev18-py2.7-nspkg.pth
odoo9_addon_mrp_bom_note-9.0.1.0.0.99.dev18.dist-info/METADATA
odoo9_addon_mrp_bom_note-9.0.1.0.0.99.dev18.dist-info/RECORD
odoo9_addon_mrp_bom_note-9.0.1.0.0.99.dev18.dist-info/WHEEL
odoo9_addon_mrp_bom_note-9.0.1.0.0.99.dev18.dist-info/namespace_packages.txt
odoo9_addon_mrp_bom_note-9.0.1.0.0.99.dev18.dist-info/top_level.txt
odoo_addons/mrp_bom_note/README.rst
odoo_addons/mrp_bom_note/__init__.py
odoo_addons/mrp_bom_note/__openerp__.py
odoo_addons/mrp_bom_note/i18n/ar.po
odoo_addons/mrp_bom_note/i18n/bs.po
odoo_addons/mrp_bom_note/i18n/ca.po
odoo_addons/mrp_bom_note/i18n/ca_ES.po
odoo_addons/mrp_bom_note/i18n/cs.po
odoo_addons/mrp_bom_note/i18n/de.po
odoo_addons/mrp_bom_note/i18n/en_GB.po
odoo_addons/mrp_bom_note/i18n/en_US.po
odoo_addons/mrp_bom_note/i18n/es.po
odoo_addons/mrp_bom_note/i18n/es_AR.po
odoo_addons/mrp_bom_note/i18n/es_CR.po
odoo_addons/mrp_bom_note/i18n/es_EC.po
odoo_addons/mrp_bom_note/i18n/es_ES.po
odoo_addons/mrp_bom_note/i18n/es_MX.po
odoo_addons/mrp_bom_note/i18n/es_VE.po
odoo_addons/mrp_bom_note/i18n/et.po
odoo_addons/mrp_bom_note/i18n/fi.po
odoo_addons/mrp_bom_note/i18n/fr.po
odoo_addons/mrp_bom_note/i18n/gl.po
odoo_addons/mrp_bom_note/i18n/hr.po
odoo_addons/mrp_bom_note/i18n/hu.po
odoo_addons/mrp_bom_note/i18n/it.po
odoo_addons/mrp_bom_note/i18n/ja.po
odoo_addons/mrp_bom_note/i18n/lt.po
odoo_addons/mrp_bom_note/i18n/mk.po
odoo_addons/mrp_bom_note/i18n/mn.po
odoo_addons/mrp_bom_note/i18n/mrp_bom_note.pot
odoo_addons/mrp_bom_note/i18n/nb.po
odoo_addons/mrp_bom_note/i18n/nl.po
odoo_addons/mrp_bom_note/i18n/nl_BE.po
odoo_addons/mrp_bom_note/i18n/pl.po
odoo_addons/mrp_bom_note/i18n/pt.po
odoo_addons/mrp_bom_note/i18n/pt_BR.po
odoo_addons/mrp_bom_note/i18n/pt_PT.po
odoo_addons/mrp_bom_note/i18n/ro.po
odoo_addons/mrp_bom_note/i18n/ru.po
odoo_addons/mrp_bom_note/i18n/sl.po
odoo_addons/mrp_bom_note/i18n/sr@latin.po
odoo_addons/mrp_bom_note/i18n/sv.po
odoo_addons/mrp_bom_note/i18n/th.po
odoo_addons/mrp_bom_note/i18n/tr.po
odoo_addons/mrp_bom_note/i18n/tr_TR.po
odoo_addons/mrp_bom_note/i18n/vi.po
odoo_addons/mrp_bom_note/i18n/zh_CN.po
odoo_addons/mrp_bom_note/i18n/zh_TW.po
odoo_addons/mrp_bom_note/models/__init__.py
odoo_addons/mrp_bom_note/models/mrp_bom.py
