Metadata-Version: 2.1
Name: odoo9-addon-mrp-bom-note
Version: 9.0.1.0.0.99.dev18
Summary: Notes in Bill of Materials
Home-page: http://www.odoomrp.com
Author: AvanzOSC,Tecnativa, Odoo Community Association (OCA)
Author-email: support@odoo-community.org
License: UNKNOWN
Platform: UNKNOWN
Classifier: Programming Language :: Python
Classifier: Framework :: Odoo
Requires-Python: ~=2.7
Requires-Dist: odoo (<9.1a,>=9.0a)
